Metadata-Version: 2.1
Name: coifstackcommons
Version: 1.0
Home-page: https://github.com/Urtats-Code/coifstack-commons
Download-URL: https://github.com/Urtats-Code/coifstack-commons/archive/refs/tags/v_02.tar.gz
Author: coifstackcommons
Author-email: urtatsberrocal@gmail.com
License: MIT
Keywords: utils,authentification,response,validation
Classifier: Development Status :: 3 - Alpha
Classifier: Intended Audience :: Developers
Classifier: Topic :: Software Development :: Build Tools
Classifier: License :: OSI Approved :: MIT License
Classifier: Programming Language :: Python :: 3
